assertize.py
assertize-0.2.0.dist-info/entry_points.txt
assertize-0.2.0.dist-info/WHEEL
assertize-0.2.0.dist-info/METADATA
assertize-0.2.0.dist-info/RECORD
